src/sources/conv.v
module conv(
input clk,
input ready,
input [7:0] fifo1_data_i,
input [7:0] fifo2_data_i,
input [7:0] fifo3_data_i,
output reg [15:0] data_o,
output reg done
);

reg [7:0] buffer1 [2:0];
reg [7:0] buffer2 [2:0];
reg [7:0] buffer3 [2:0];
reg [3:0] count = 4'b0000;

initial begin
  done <= 1'b0;
  data_o <= 8'b0000_0000;
end

always @(posedge clk) begin
  if (ready == 1) begin
    buffer1[count] <= fifo1_data_i;
    buffer2[count] <= fifo2_data_i;
    buffer3[count] <= fifo3_data_i;
    count = count + 4'b0001;
  end
  if (count == 4'b0011) begin
      count = 4'b0000;
      done <= 1'b1;
  end
  if (done) begin
      data_o <= ((buffer1[2]  - buffer1[0]) + ((buffer2[2] * 2) - (buffer2[0] * 2)) + (buffer3[2]  - buffer3[0] ));
      done <= 1'b0;
    end
end
endmodule

src/testbenches/hold.v
module hold(
input clk,
input [7:0] fifo1_data_i,
input [7:0] fifo2_data_i,
input [7:0] fifo3_data_i,
input ready_i,

output reg [7:0] fifo1_data_o,
output reg [7:0] fifo2_data_o,
output reg [7:0] fifo3_data_o,
output reg idle_o,
output reg ready_o,
output reg done_o
);

reg [7:0] hold_data1 [2:0];
reg [7:0] hold_data2 [2:0];
reg [7:0] hold_data3 [2:0];
reg [7:0] COL_COUNT;
reg WINDOW_FLAG;
reg [7:0] HSYNC;
reg [7:0] W_COUNT;
reg MODE;

initial begin
  fifo1_data_o <= 8'b0000_0000;
  fifo2_data_o <= 8'b0000_0000;
  fifo3_data_o <= 8'b0000_0000;
  idle_o <= 1'b1;
  ready_o <= 1'b0;
  done_o <= 1'b0;
  COL_COUNT = 8'b0000_0000;
  WINDOW_FLAG = 1'b0;
  HSYNC = 8'b0000_0010;
  W_COUNT = 8'b0000_0000;
  MODE = 1'b0;
end

always @(posedge clk) begin
  if (ready_i == 1'b1 && MODE == 1'b0) begin
    done_o <= 1'b0;
    hold_data1[0] = hold_data1[1];
    hold_data1[1] = hold_data1[2];
    hold_data1[2] = fifo1_data_i;

    hold_data2[0] = hold_data2[1];
    hold_data2[1] = hold_data2[2];
    hold_data2[2] = fifo2_data_i;

    hold_data3[0] = hold_data3[1];
    hold_data3[1] = hold_data3[2];
    hold_data3[2] = fifo3_data_i;
    COL_COUNT = COL_COUNT + 8'b0000_0001;

    if (COL_COUNT == 8'b0000_0011) begin
      WINDOW_FLAG = 1'b1;
    end
    if (WINDOW_FLAG == 1'b1) begin
      idle_o <= 1'b0;
      ready_o <= 1'b0;
      COL_COUNT = -1;
      MODE = 1'b1;
    end
  end
  if (W_COUNT == 8'b0000_0011) begin
    idle_o <= 1'b1;
    ready_o <= 1'b0;
    W_COUNT = 8'b0000_0000;
    MODE = 1'b0;
    HSYNC = HSYNC + 8'b0000_0001;
    if (HSYNC == 8'b0000_0101) begin
      done_o <= 1'b1;
      WINDOW_FLAG = 1'b0;
      HSYNC = 8'b0000_0010;
      hold_data1[0] = 8'b0000_0000;
      hold_data1[1] = 8'b0000_0000;
      hold_data1[2] = 8'b0000_0000;
      hold_data2[0] = 8'b0000_0000;
      hold_data2[1] = 8'b0000_0000;
      hold_data2[2] = 8'b0000_0000;
      hold_data3[0] = 8'b0000_0000;
      hold_data3[1] = 8'b0000_0000;
      hold_data3[2] = 8'b0000_0000;
      fifo1_data_o <= 8'b0000_0000;
      fifo2_data_o <= 8'b0000_0000;
      fifo3_data_o <= 8'b0000_0000;
    end
  end
  if (MODE == 1'b1) begin
    if (W_COUNT < 8'b0000_0011) begin
      idle_o <= 1'b0;
      ready_o <= 1'b1;
      fifo1_data_o <= hold_data1[W_COUNT];
      fifo2_data_o <= hold_data2[W_COUNT];
      fifo3_data_o <= hold_data3[W_COUNT];
      W_COUNT = W_COUNT + 8'b0000_0001;
    end
  end
end
endmodule

src/sources/Fifo.v
module Fifo(
input clk,
input data_valid,
input [7:0] data_i,
input idle_i,
input done_i,

output reg [7:0] fifo1_data_o,
output reg [7:0] fifo2_data_o,
output reg [7:0] fifo3_data_o,
output reg idle,
output reg ready,
output reg done
);

parameter WIDTH = 5; // Width of the image
parameter HEIGHT = 5; // Height of the image
integer i;

reg MODE; // Read/Write Mode
reg [7:0] R_COUNT;  // Read Counter
reg [7:0] W_COUNT;  // Write Counter
reg WINDOW_FLAG;
reg [7:0] COL_COUNT;
reg [7:0] VSYNC;
reg [7:0] fifo1 [WIDTH-1:0];
reg [7:0] fifo2 [WIDTH-1:0];
reg [7:0] fifo3 [WIDTH-1:0];
initial begin
  fifo1_data_o <= 8'b0000_0000;
  fifo2_data_o <= 8'b0000_0000;
  fifo3_data_o <= 8'b0000_0000;
  idle <= 1'b1;
  ready <= 1'b0;
  done <= 1'b0;
  MODE = 1'b0;
  COL_COUNT = 8'b0000_0000;
  W_COUNT = 8'b0000_0000;
  WINDOW_FLAG = 1'b0;
  VSYNC = 8'b0000_0010;
end

always @(posedge clk) begin
  if (data_valid == 1'b1 && MODE == 1'b0) begin
    fifo1[0] = fifo1[1];
    fifo1[1] = fifo1[2];
    fifo1[2] = fifo1[3];
    fifo1[3] = fifo1[4];
    fifo1[4] = fifo2[0];
    fifo2[0] = fifo2[1];
    fifo2[1] = fifo2[2];
    fifo2[2] = fifo2[3];
    fifo2[3] = fifo2[4];
    fifo2[4] = fifo3[0];
    fifo3[0] = fifo3[1];
    fifo3[1] = fifo3[2];
    fifo3[2] = fifo3[3];
    fifo3[3] = fifo3[4];
    fifo3[4] = data_i;
    COL_COUNT = COL_COUNT + 8'b0000_0001;
    if (COL_COUNT == 3 * WIDTH) begin
      WINDOW_FLAG = 1'b1;
      COL_COUNT = WIDTH;
    end
    if (WINDOW_FLAG == 1'b1 && COL_COUNT == WIDTH) begin
      idle <= 1'b0;
      ready <= 1'b0;
      COL_COUNT = 8'b0000_0000;
      MODE = 1'b1;
    end
  end
  if (data_valid == 1'b0 && MODE == 1'b1  && idle_i == 1'b1) begin
    idle <= 1'b0;
    ready <= 1'b1;
    if (W_COUNT < WIDTH) begin
      fifo1_data_o <= fifo1[W_COUNT];
      fifo2_data_o <= fifo2[W_COUNT];
      fifo3_data_o <= fifo3[W_COUNT];
      W_COUNT = W_COUNT + 8'b0000_0001;
    end

    if (W_COUNT == WIDTH && done_i == 1'b1) begin
      ready <= 1'b0;
      idle <= 1'b1;
      W_COUNT = 8'b0000_0000;
      MODE = 1'b0;
      VSYNC = VSYNC + 8'b0000_0001;
      if (VSYNC == 8'b0000_0101) begin
        done <= 1'b1;
      end
    end
  end
end
endmodule

src/sources/fifo_conv_top.v
`include "hold.v"
`include "Fifo.v"
`include "conv.v"

module fifo_conv_top(
input clk,
input data_valid,
input [7:0] data_i,

output wire idle,
output wire done,
output wire [15:0] data_o,
output wire conv_done
);

wire [7:0] fifo1_data_o;
wire [7:0] fifo2_data_o;
wire [7:0] fifo3_data_o;
wire [7:0] fifo1_data_i;
wire [7:0] fifo2_data_i;
wire [7:0] fifo3_data_i;
wire ready;
wire idle_o;
wire ready_o;
wire done_o;


Fifo myFifo(.clk(clk), .data_valid(data_valid), .data_i(data_i), .fifo1_data_o(fifo1_data_i), .fifo2_data_o(fifo2_data_i), .fifo3_data_o(fifo3_data_i), .idle(idle), .idle_i(idle_o), .ready(ready), .done(done), .done_i(done_o));

hold myHold(.clk(clk), .fifo1_data_i(fifo1_data_i), .fifo2_data_i(fifo2_data_i), .fifo3_data_i(fifo3_data_i), .fifo1_data_o(fifo1_data_o), .fifo2_data_o(fifo2_data_o), .fifo3_data_o(fifo3_data_o), .ready_i(ready), .idle_o(idle_o), .ready_o(ready_o), .done_o(done_o));

conv myConv(.clk(clk), .ready(ready_o), .fifo1_data_i(fifo1_data_o), .fifo2_data_i(fifo2_data_o), .fifo3_data_i(fifo3_data_o), .data_o(data_o), .done(conv_done));

endmodule

src/testbenches/fifo_conv_top_tb.v
`include "fifo_conv_top.v"

module fifo_conv_top_tb();
reg clk;
reg data_valid;
reg [7:0] data_i;
wire idle;
wire done;
wire [7:0] fifo1_data_o;
wire [7:0] fifo2_data_o;
wire [7:0] fifo3_data_o;
wire [15:0] data_o;
wire ready;
wire done_o;

reg [7:0] mem [24:0];
reg [7:0] i;

fifo_conv_top myTop(.clk(clk), .data_valid(data_valid), .data_i(data_i), .idle(idle), .done(done), .data_o(data_o), .conv_done(done_o));

initial begin
  clk = 1'b0;
  forever #5 clk = ~clk;
end

initial begin
  data_valid = 1'b0;
  data_i = 8'b0000_0000;
  i = 8'b0000_0000;
  $readmemh("data.txt", mem);
end

always @(posedge clk) begin
  #10
  if (idle) begin
    $display("%h %b", mem[i], i);
    data_valid = 1'b1;
    data_i = mem[i];
    i = i + 8'b0000_0001;
    if (i== 8'b0001_1010) begin
      data_i = 8'b0000_0000;
    end
    if (done) begin
      $finish;
    end
  end
  else begin
    data_valid = 1'b0;
  end
  $dumpfile("Top.vcd");
  $dumpvars(0, fifo_conv_top_tb);
end
endmodule

src/testbenches/Top.vcd
$date
	Thu Jan 21 22:46:18 2021
$end
$version
	Icarus Verilog
$end
$timescale
	1s
$end
$scope module fifo_conv_top_tb $end
$var wire 1 ! idle $end
$var wire 1 " done_o $end
$var wire 1 # done $end
$var wire 16 $ data_o [15:0] $end
$var reg 1 % clk $end
$var reg 8 & data_i [7:0] $end
$var reg 1 ' data_valid $end
$var reg 8 ( i [7:0] $end
$scope module myTop $end
$var wire 1 % clk $end
$var wire 8 ) data_i [7:0] $end
$var wire 1 ' data_valid $end
$var wire 1 * ready_o $end
$var wire 1 + ready $end
$var wire 1 , idle_o $end
$var wire 1 ! idle $end
$var wire 8 - fifo3_data_o [7:0] $end
$var wire 8 . fifo3_data_i [7:0] $end
$var wire 8 / fifo2_data_o [7:0] $end
$var wire 8 0 fifo2_data_i [7:0] $end
$var wire 8 1 fifo1_data_o [7:0] $end
$var wire 8 2 fifo1_data_i [7:0] $end
$var wire 1 3 done_o $end
$var wire 1 # done $end
$var wire 16 4 data_o [15:0] $end
$var wire 1 " conv_done $end
$scope module myConv $end
$var wire 1 % clk $end
$var wire 1 * ready $end
$var wire 8 5 fifo3_data_i [7:0] $end
$var wire 8 6 fifo2_data_i [7:0] $end
$var wire 8 7 fifo1_data_i [7:0] $end
$var reg 4 8 count [3:0] $end
$var reg 16 9 data_o [15:0] $end
$var reg 1 " done $end
$upscope $end
$scope module myFifo $end
$var wire 1 % clk $end
$var wire 8 : data_i [7:0] $end
$var wire 1 ' data_valid $end
$var wire 1 , idle_i $end
$var wire 1 3 done_i $end
$var reg 8 ; COL_COUNT [7:0] $end
$var reg 1 < MODE $end
$var reg 8 = VSYNC [7:0] $end
$var reg 1 > WINDOW_FLAG $end
$var reg 8 ? W_COUNT [7:0] $end
$var reg 1 # done $end
$var reg 8 @ fifo1_data_o [7:0] $end
$var reg 8 A fifo2_data_o [7:0] $end
$var reg 8 B fifo3_data_o [7:0] $end
$var reg 1 ! idle $end
$var reg 1 + ready $end
$upscope $end
$scope module myHold $end
$var wire 1 % clk $end
$var wire 8 C fifo1_data_i [7:0] $end
$var wire 8 D fifo2_data_i [7:0] $end
$var wire 8 E fifo3_data_i [7:0] $end
$var wire 1 + ready_i $end
$var reg 8 F COL_COUNT [7:0] $end
$var reg 8 G HSYNC [7:0] $end
$var reg 1 H MODE $end
$var reg 1 I WINDOW_FLAG $end
$var reg 8 J W_COUNT [7:0] $end
$var reg 1 3 done_o $end
$var reg 8 K fifo1_data_o [7:0] $end
$var reg 8 L fifo2_data_o [7:0] $end
$var reg 8 M fifo3_data_o [7:0] $end
$var reg 1 , idle_o $end
$var reg 1 * ready_o $end
$upscope $end
$upscope $end
$upscope $end
$enddefinitions $end
#15
$dumpvars
b0 M
b0 L
b0 K
b0 J
0I
0H
b10 G
b0 F
b0 E
b0 D
b0 C
b0 B
b0 A
b0 @
b0 ?
0>
b10 =
0<
b1 ;
b0 :
b0 9
b0 8
b0 7
b0 6
b0 5
b0 4
03
b0 2
b0 1
b0 0
b0 /
b0 .
b0 -
1,
0+
0*
b0 )
b1 (
1'
b0 &
1%
b0 $
0#
0"
1!
$end
#20
0%
#25
b10 ;
1%
b10 (
b10001 &
b10001 )
b10001 :
#30
0%
#35
b11 ;
1%
b11 (
b1100 &
b1100 )
b1100 :
#40
0%
#45
b100 ;
1%
b100 (
b1000011 &
b1000011 )
b1000011 :
#50
0%
#55
b101 ;
1%
b101 (
b11110100 &
b11110100 )
b11110100 :
#60
0%
#65
b110 ;
1%
b110 (
b11 &
b11 )
b11 :
#70
0%
#75
b111 ;
1%
b111 (
b1111000 &
b1111000 )
b1111000 :
#80
0%
#85
b1000 ;
1%
b1000 (
b11011110 &
b11011110 )
b11011110 :
#90
0%
#95
b1001 ;
1%
b1001 (
b10001 &
b10001 )
b10001 :
#100
0%
#105
b1010 ;
1%
b1010 (
b1101100 &
b1101100 )
b1101100 :
#110
0%
#115
b1011 ;
1%
b1011 (
b10101010 &
b10101010 )
b10101010 :
#120
0%
#125
b1100 ;
1%
b1100 (
b110100 &
b110100 )
b110100 :
#130
0%
#135
b1101 ;
1%
b1101 (
b1100001 &
b1100001 )
b1100001 :
#140
0%
#145
b1110 ;
1%
b1110 (
b101110 &
b101110 )
b101110 :
#150
0%
#155
0!
1<
1>
b0 ;
1%
b1111 (
b10011011 &
b10011011 )
b10011011 :
#160
0%
#165
b10101010 .
b10101010 B
b10101010 E
b11 0
b11 A
b11 D
1+
b1 ?
1%
0'
#170
0%
#175
b110100 .
b110100 B
b110100 E
b1111000 0
b1111000 A
b1111000 D
b10001 2
b10001 @
b10001 C
b1 F
b10 ?
1%
#180
0%
#185
b1100001 .
b1100001 B
b1100001 E
b11011110 0
b11011110 A
b11011110 D
b1100 2
b1100 @
b1100 C
b11 ?
b10 F
1%
#190
0%
#195
b10101010 -
b10101010 5
b10101010 M
b11 /
b11 6
b11 L
1*
0,
b101110 .
b101110 B
b101110 E
b10001 0
b10001 A
b10001 D
b1000011 2
b1000011 @
b1000011 C
b1 J
1H
1I
b11111111 F
b100 ?
1%
#200
0%
#205
b110100 -
b110100 5
b110100 M
b1111000 /
b1111000 6
b1111000 L
b10001 1
b10001 7
b10001 K
b10 J
b1 8
1%
#210
0%
#215
b1100001 -
b1100001 5
b1100001 M
b11011110 /
b11011110 6
b11011110 L
b1100 1
b1100 7
b1100 K
b10 8
b11 J
1%
#220
0%
#225
0*
1,
1"
b11 G
0H
b0 J
b0 8
1%
#230
0%
#235
0"
b101111001 $
b101111001 4
b101111001 9
b110100 -
b110100 5
b110100 M
b1111000 /
b1111000 6
b1111000 L
b10001 1
b10001 7
b10001 K
1*
0,
b10011011 .
b10011011 B
b10011011 E
b1101100 0
b1101100 A
b1101100 D
b11110100 2
b11110100 @
b11110100 C
b1 J
1H
b11111111 F
b101 ?
1%
#240
0%
#245
b1100001 -
b1100001 5
b1100001 M
b11011110 /
b11011110 6
b11011110 L
b1100 1
b1100 7
b1100 K
b10 J
b1 8
1%
#250
0%
#255
b101110 -
b101110 5
b101110 M
b10001 /
b10001 6
b10001 L
b1000011 1
b1000011 7
b1000011 K
b10 8
b11 J
1%
#260
0%
#265
0*
1,
1"
b100 G
0H
b0 J
b0 8
1%
#270
0%
#275
0"
b1111111101011110 $
b1111111101011110 4
b1111111101011110 9
b1100001 -
b1100001 5
b1100001 M
b11011110 /
b11011110 6
b11011110 L
b1100 1
b1100 7
b1100 K
1*
0,
b1 J
1H
b11111111 F
1%
#280
0%
#285
b101110 -
b101110 5
b101110 M
b10001 /
b10001 6
b10001 L
b1000011 1
b1000011 7
b1000011 K
b10 J
b1 8
1%
#290
0%
#295
b10011011 -
b10011011 5
b10011011 M
b1101100 /
b1101100 6
b1101100 L
b11110100 1
b11110100 7
b11110100 K
b10 8
b11 J
1%
#300
0%
#305
b0 -
b0 5
b0 M
b0 /
b0 6
b0 L
b0 1
b0 7
b0 K
13
0*
1,
1"
0I
b10 G
0H
b0 J
b0 8
1%
#310
0%
#315
0"
b111110 $
b111110 4
b111110 9
03
1!
0+
b0 F
b11 =
0<
b0 ?
1%
#320
0%
#325
b1 ;
1%
b10000 (
b1110 &
b1110 )
b1110 :
1'
#330
0%
#335
b10 ;
1%
b10001 (
b11111 &
b11111 )
b11111 :
#340
0%
#345
b11 ;
1%
b10010 (
b1000101 &
b1000101 )
b1000101 :
#350
0%
#355
b100 ;
1%
b10011 (
b1011111 &
b1011111 )
b1011111 :
#360
0%
#365
0!
1<
b0 ;
1%
b10100 (
b11110011 &
b11110011 )
b11110011 :
#370
0%
#375
b1110 .
b1110 B
b1110 E
b10101010 0
b10101010 A
b10101010 D
b11 2
b11 @
b11 C
1+
b1 ?
1%
0'
#380
0%
#385
b11111 .
b11111 B
b11111 E
b110100 0
b110100 A
b110100 D
b1111000 2
b1111000 @
b1111000 C
b10 ?
b1 F
1%
#390
0%
#395
b1000101 .
b1000101 B
b1000101 E
b1100001 0
b1100001 A
b1100001 D
b11011110 2
b11011110 @
b11011110 C
b10 F
b11 ?
1%
#400
0%
#405
b1011111 .
b1011111 B
b1011111 E
b101110 0
b101110 A
b101110 D
b10001 2
b10001 @
b10001 C
b1110 -
b1110 5
b1110 M
b10101010 /
b10101010 6
b10101010 L
b11 1
b11 7
b11 K
1*
0,
b100 ?
b1 J
1H
1I
b11111111 F
1%
#410
0%
#415
b11111 -
b11111 5
b11111 M
b110100 /
b110100 6
b110100 L
b1111000 1
b1111000 7
b1111000 K
b1 8
b10 J
1%
#420
0%
#425
b1000101 -
b1000101 5
b1000101 M
b1100001 /
b1100001 6
b1100001 L
b11011110 1
b11011110 7
b11011110 K
b11 J
b10 8
1%
#430
0%
#435
1"
0*
1,
b0 8
b11 G
0H
b0 J
1%
#440
0%
#445
b11110011 .
b11110011 B
b11110011 E
b10011011 0
b10011011 A
b10011011 D
b1101100 2
b1101100 @
b1101100 C
b11111 -
b11111 5
b11111 M
b110100 /
b110100 6
b110100 L
b1111000 1
b1111000 7
b1111000 K
1*
0,
0"
b10000000 $
b10000000 4
b10000000 9
b101 ?
b1 J
1H
b11111111 F
1%
#450
0%
#455
b1000101 -
b1000101 5
b1000101 M
b1100001 /
b1100001 6
b1100001 L
b11011110 1
b11011110 7
b11011110 K
b1 8
b10 J
1%
#460
0%
#465
b1011111 -
b1011111 5
b1011111 M
b101110 /
b101110 6
b101110 L
b10001 1
b10001 7
b10001 K
b11 J
b10 8
1%
#470
0%
#475
1"
0*
1,
b0 8
b100 G
0H
b0 J
1%
#480
0%
#485
b1000101 -
b1000101 5
b1000101 M
b1100001 /
b1100001 6
b1100001 L
b11011110 1
b11011110 7
b11011110 K
1*
0,
0"
b1111111111001101 $
b1111111111001101 4
b1111111111001101 9
b1 J
1H
b11111111 F
1%
#490
0%
#495
b1011111 -
b1011111 5
b1011111 M
b101110 /
b101110 6
b101110 L
b10001 1
b10001 7
b10001 K
b1 8
b10 J
1%
#500
0%
#505
b11110011 -
b11110011 5
b11110011 M
b10011011 /
b10011011 6
b10011011 L
b1101100 1
b1101100 7
b1101100 K
b11 J
b10 8
1%
#510
0%
#515
1"
b0 -
b0 5
b0 M
b0 /
b0 6
b0 L
b0 1
b0 7
b0 K
13
0*
1,
b0 8
0I
b10 G
0H
b0 J
1%
#520
0%
#525
1!
0+
03
0"
b10110000 $
b10110000 4
b10110000 9
b100 =
0<
b0 ?
b0 F
1%
#530
0%
#535
b1 ;
1%
b10101 (
b1111000 &
b1111000 )
b1111000 :
1'
#540
0%
#545
b10 ;
1%
b10110 (
b10000010 &
b10000010 )
b10000010 :
#550
0%
#555
b11 ;
1%
b10111 (
b1010 &
b1010 )
b1010 :
#560
0%
#565
b100 ;
1%
b11000 (
b1000100 &
b1000100 )
b1000100 :
#570
0%
#575
0!
1<
b0 ;
1%
b11001 (
b110101 &
b110101 )
b110101 :
#580
0%
#585
b1111000 .
b1111000 B
b1111000 E
b1110 0
b1110 A
b1110 D
b10101010 2
b10101010 @
b10101010 C
1+
b1 ?
1%
0'
#590
0%
#595
b10000010 .
b10000010 B
b10000010 E
b11111 0
b11111 A
b11111 D
b110100 2
b110100 @
b110100 C
b1 F
b10 ?
1%
#600
0%
#605
b1010 .
b1010 B
b1010 E
b1000101 0
b1000101 A
b1000101 D
b1100001 2
b1100001 @
b1100001 C
b11 ?
b10 F
1%
#610
0%
#615
b1111000 -
b1111000 5
b1111000 M
b1110 /
b1110 6
b1110 L
b10101010 1
b10101010 7
b10101010 K
1*
0,
b1000100 .
b1000100 B
b1000100 E
b1011111 0
b1011111 A
b1011111 D
b101110 2
b101110 @
b101110 C
b1 J
1H
1I
b11111111 F
b100 ?
1%
#620
0%
#625
b10000010 -
b10000010 5
b10000010 M
b11111 /
b11111 6
b11111 L
b110100 1
b110100 7
b110100 K
b10 J
b1 8
1%
#630
0%
#635
b1010 -
b1010 5
b1010 M
b1000101 /
b1000101 6
b1000101 L
b1100001 1
b1100001 7
b1100001 K
b10 8
b11 J
1%
#640
0%
#645
0*
1,
1"
b11 G
0H
b0 J
b0 8
1%
#650
0%
#655
0"
b1111111110110111 $
b1111111110110111 4
b1111111110110111 9
b10000010 -
b10000010 5
b10000010 M
b11111 /
b11111 6
b11111 L
b110100 1
b110100 7
b110100 K
1*
0,
b110101 .
b110101 B
b110101 E
b11110011 0
b11110011 A
b11110011 D
b10011011 2
b10011011 @
b10011011 C
b1 J
1H
b11111111 F
b101 ?
1%
#660
0%
#665
b1010 -
b1010 5
b1010 M
b1000101 /
b1000101 6
b1000101 L
b1100001 1
b1100001 7
b1100001 K
b10 J
b1 8
1%
#670
0%
#675
b1000100 -
b1000100 5
b1000100 M
b1011111 /
b1011111 6
b1011111 L
b101110 1
b101110 7
b101110 K
b10 8
b11 J
1%
#680
0%
#685
0*
1,
1"
b100 G
0H
b0 J
b0 8
1%
#690
0%
#695
0"
b111100 $
b111100 4
b111100 9
b1010 -
b1010 5
b1010 M
b1000101 /
b1000101 6
b1000101 L
b1100001 1
b1100001 7
b1100001 K
1*
0,
b1 J
1H
b11111111 F
1%
#700
0%
#705
b1000100 -
b1000100 5
b1000100 M
b1011111 /
b1011111 6
b1011111 L
b101110 1
b101110 7
b101110 K
b10 J
b1 8
1%
#710
0%
#715
b110101 -
b110101 5
b110101 M
b11110011 /
b11110011 6
b11110011 L
b10011011 1
b10011011 7
b10011011 K
b10 8
b11 J
1%
#720
0%
#725
b0 -
b0 5
b0 M
b0 /
b0 6
b0 L
b0 1
b0 7
b0 K
13
0*
1,
1"
0I
b10 G
0H
b0 J
b0 8
1%
#730
0%
#735
0"
b111000001 $
b111000001 4
b111000001 9
03
1#
1!
0+
b0 F
b101 =
0<
b0 ?
1%
#740
0%
#745
b1 ;
1%
b11010 (
b0 &
b0 )
b0 :
1'
